lgnpy/GaussianBP.py
lgnpy/Graph.py
lgnpy/LinearGaussian.py
lgnpy/LinearGaussianExperimental.py
lgnpy/__init__.py
lgnpy/logging_config.py
tests/__init__.py
tests/test_LinearGaussian.py
tests/test_lgnpy.py
LGNpy-1.0.0.dist-info/LICENSE
LGNpy-1.0.0.dist-info/METADATA
LGNpy-1.0.0.dist-info/WHEEL
LGNpy-1.0.0.dist-info/top_level.txt
LGNpy-1.0.0.dist-info/RECORD
