Metadata-Version: 2.1
Name: LGNpy
Version: 1.0.0
Summary: Linear Gaussian Networks - Inference, Parameter Learning and Representation
Home-page: https://github.com/ostwalprasad/lgnpy
Author: Prasad Ostwal
Author-email: prasadostwal@gmail.com
License: UNKNOWN
Keywords: linear gaussian networks representation inference bayesian
Platform: UNKNOWN
Classifier: Programming Language :: Python :: 3
Classifier: License :: OSI Approved :: MIT License
Classifier: Operating System :: OS Independent
Classifier: Topic :: Scientific/Engineering :: Artificial Intelligence
Classifier: Intended Audience :: Developers
Classifier: Intended Audience :: Science/Research
Classifier: Development Status :: 5 - Production/Stable
Requires-Python: >=3.6
Requires-Dist: numpy
Requires-Dist: pandas
Requires-Dist: networkx (>=2.3)
Requires-Dist: pydot
